pymc/__init__.py
pymc/aesaraf.py
pymc/blocking.py
pymc/data.py
pymc/exceptions.py
pymc/func_utils.py
pymc/initial_point.py
pymc/math.py
pymc/model.py
pymc/model_graph.py
pymc/parallel_sampling.py
pymc/printing.py
pymc/sampling.py
pymc/sampling_jax.py
pymc/util.py
pymc/vartypes.py
pymc/backends/__init__.py
pymc/backends/arviz.py
pymc/backends/base.py
pymc/backends/ndarray.py
pymc/backends/report.py
pymc/bart/__init__.py
pymc/bart/bart.py
pymc/bart/pgbart.py
pymc/bart/tree.py
pymc/bart/utils.py
pymc/distributions/__init__.py
pymc/distributions/bound.py
pymc/distributions/censored.py
pymc/distributions/continuous.py
pymc/distributions/discrete.py
pymc/distributions/dist_math.py
pymc/distributions/distribution.py
pymc/distributions/logprob.py
pymc/distributions/mixture.py
pymc/distributions/multivariate.py
pymc/distributions/shape_utils.py
pymc/distributions/simulator.py
pymc/distributions/timeseries.py
pymc/distributions/transforms.py
pymc/gp/__init__.py
pymc/gp/cov.py
pymc/gp/gp.py
pymc/gp/mean.py
pymc/gp/util.py
pymc/ode/__init__.py
pymc/ode/ode.py
pymc/ode/utils.py
pymc/plots/__init__.py
pymc/smc/__init__.py
pymc/smc/sample_smc.py
pymc/smc/smc.py
pymc/stats/__init__.py
pymc/step_methods/__init__.py
pymc/step_methods/arraystep.py
pymc/step_methods/compound.py
pymc/step_methods/elliptical_slice.py
pymc/step_methods/metropolis.py
pymc/step_methods/mlda.py
pymc/step_methods/sgmcmc.py
pymc/step_methods/slicer.py
pymc/step_methods/step_sizes.py
pymc/step_methods/hmc/__init__.py
pymc/step_methods/hmc/base_hmc.py
pymc/step_methods/hmc/hmc.py
pymc/step_methods/hmc/integration.py
pymc/step_methods/hmc/nuts.py
pymc/step_methods/hmc/quadpotential.py
pymc/tests/__init__.py
pymc/tests/backend_fixtures.py
pymc/tests/checks.py
pymc/tests/conftest.py
pymc/tests/helpers.py
pymc/tests/models.py
pymc/tests/sampler_fixtures.py
pymc/tests/test_aesaraf.py
pymc/tests/test_bart.py
pymc/tests/test_data_container.py
pymc/tests/test_dist_math.py
pymc/tests/test_distributions.py
pymc_nightly-4.0.0b2.dev20220304.dist-info/LICENSE
pymc_nightly-4.0.0b2.dev20220304.dist-info/METADATA
pymc_nightly-4.0.0b2.dev20220304.dist-info/WHEEL
pymc_nightly-4.0.0b2.dev20220304.dist-info/top_level.txt
pymc_nightly-4.0.0b2.dev20220304.dist-info/RECORD
