Metadata-Version: 2.1
Name: pymc-nightly
Version: 4.0.0b2.dev20220304
Summary: Probabilistic Programming in Python: Bayesian Modeling and Probabilistic Machine Learning with Aesara
Home-page: http://github.com/pymc-devs/pymc
Maintainer: PyMC Developers
Maintainer-email: pymc.devs@gmail.com
License: Apache License, Version 2.0
Platform: UNKNOWN
Classifier: Development Status :: 5 - Production/Stable
Classifier: Programming Language :: Python
Classifier: Programming Language :: Python :: 3
Classifier: Programming Language :: Python :: 3.7
Classifier: Programming Language :: Python :: 3.8
Classifier: Programming Language :: Python :: 3.9
Classifier: License :: OSI Approved :: Apache Software License
Classifier: Intended Audience :: Science/Research
Classifier: Topic :: Scientific/Engineering
Classifier: Topic :: Scientific/Engineering :: Mathematics
Classifier: Operating System :: OS Independent
Requires-Python: >=3.7
License-File: LICENSE
Requires-Dist: aeppl (==0.0.26)
Requires-Dist: aesara (==2.4.0)
Requires-Dist: arviz (>=0.11.4)
Requires-Dist: cachetools (>=4.2.1)
Requires-Dist: cloudpickle
Requires-Dist: fastprogress (>=0.2.0)
Requires-Dist: numpy (>=1.15.0)
Requires-Dist: pandas (>=0.24.0)
Requires-Dist: scipy (>=1.4.1)
Requires-Dist: typing-extensions (>=3.7.4)
